xgridfit/__init__.py
xgridfit/version.py
xgridfit/xgfUFOWriter.py
xgridfit/xgridfit-backup.py
xgridfit/xgridfit.py
xgridfit/ygridfit.py
xgridfit/Schemas/xgridfit-sh.rnc
xgridfit/Schemas/xgridfit-sh.rng
xgridfit/Schemas/xgridfit.rnc
xgridfit/Schemas/xgridfit.rng
xgridfit/Schemas/xgridfit.xsd
xgridfit/Schemas/xi.xsd
xgridfit/Schemas/xml.xsd
xgridfit/XSL/arithmetic.xsl
xgridfit/XSL/compact.xsl
xgridfit/XSL/delta.xsl
xgridfit/XSL/expand.xsl
xgridfit/XSL/expressions.xsl
xgridfit/XSL/flow.xsl
xgridfit/XSL/func-predef.xsl
xgridfit/XSL/function.xsl
xgridfit/XSL/graphics.xsl
xgridfit/XSL/measure.xsl
xgridfit/XSL/messages.xsl
xgridfit/XSL/misc.xsl
xgridfit/XSL/move-els.xsl
xgridfit/XSL/move-lib.xsl
xgridfit/XSL/numbers.xsl
xgridfit/XSL/points.xsl
xgridfit/XSL/prep.xsl
xgridfit/XSL/primitives.xsl
xgridfit/XSL/std-vars.xsl
xgridfit/XSL/xgfdata.xml
xgridfit/XSL/xgridfit-ft.xsl
xgridfit-3.3.0.dist-info/LICENSE.txt
xgridfit-3.3.0.dist-info/METADATA
xgridfit-3.3.0.dist-info/WHEEL
xgridfit-3.3.0.dist-info/entry_points.txt
xgridfit-3.3.0.dist-info/top_level.txt
xgridfit-3.3.0.dist-info/RECORD
