Metadata-Version: 2.1
Name: xgridfit
Version: 3.3.0
Summary: An XML-based hinting language for TrueType fonts
Author-email: "Peter S. Baker" <b.tarde@mail.com>
Classifier: Programming Language :: Python :: 3
Classifier: License :: OSI Approved :: Apache Software License
Classifier: Operating System :: OS Independent
Requires-Python: >=3.10.4
License-File: LICENSE.txt
Requires-Dist: lxml (>=4.8.8)
Requires-Dist: fonttools (>=4.38.0)
Requires-Dist: setuptools (>=65.5.1)
Requires-Dist: PyYAML (>=6.0)
